fumadocs_autodoc/__init__.py
fumadocs_autodoc/mksource/__init__.py
fumadocs_autodoc/mksource/document_module.py
fumadocs_autodoc/mksource/json_encoder.py
fumadocs_autodoc/mksource/models.py
fumadocs_autodoc/mksource/simplify_docstring.py
fumadocs_autodoc/mksource/utils.py
fumadocs_autodoc-0.0.2.dist-info/METADATA
fumadocs_autodoc-0.0.2.dist-info/WHEEL
fumadocs_autodoc-0.0.2.dist-info/entry_points.txt
fumadocs_autodoc-0.0.2.dist-info/licenses/LICENSE
fumadocs_autodoc-0.0.2.dist-info/RECORD
