Metadata-Version: 2.4
Name: fumadocs-autodoc
Version: 0.0.2
Summary: Extract API documentation from source code and docstrings. For the python API extension for FumaDocs.
Author-email: zrlf <florez@ethz.ch>
License-File: LICENSE
Requires-Python: >=3.10
Requires-Dist: griffe>=1.11
